comver-0.2.0.dist-info/METADATA
comver-0.2.0.dist-info/WHEEL
comver-0.2.0.dist-info/entry_points.txt
comver/__init__.py
comver/__main__.py
comver/_cli.py
comver/_parser.py
comver/_regex/__init__.py
comver/_regex/_process.py
comver/_regex/match.py
comver/_regex/semantic.py
comver/_subcommand.py
comver/_version.py
comver/error.py
comver/plugin.py
comver/py.typed
comver/py.typed.license
comver/type_definitions.py
comver-0.2.0.dist-info/RECORD
