Metadata-Version: 2.4
Name: comver
Version: 0.2.0
Summary: Commit-based semantic versioning - highly configurable and tag-free.
Author: open-nudge
Maintainer: open-nudge
License-Expression: Apache-2.0
Classifier: Development Status :: 2 - Pre-Alpha
Classifier: Intended Audience :: Developers
Classifier: Programming Language :: Python
Classifier: Programming Language :: Python :: 3 :: Only
Classifier: Programming Language :: Python :: 3.11
Classifier: Programming Language :: Python :: 3.12
Classifier: Programming Language :: Python :: 3.13
Classifier: Topic :: Software Development :: Libraries
Classifier: Topic :: Software Development :: Libraries :: Python Modules
Classifier: Typing :: Typed
Project-URL: Changelog, https://github.com/open-nudge/comver/blob/master/CHANGELOG.md
Project-URL: Documentation, https://open-nudge.github.io/comver
Project-URL: Homepage, https://open-nudge.github.io/comver
Project-URL: Issues, https://github.com/open-nudge/comver/issues
Project-URL: Repository, https://github.com/open-nudge/comver
Requires-Python: >=3.11
Requires-Dist: loadfig>=0.1.0
Requires-Dist: GitPython>=3
Provides-Extra: hatchling
Requires-Dist: hatchling>=1.27.0; extra == "hatchling"
